README.md
setup.cfg
setup.py
powerline_exitstatus_kai/__init__.py
powerline_exitstatus_kai/segments.py
powerline_exitstatus_kai.egg-info/PKG-INFO
powerline_exitstatus_kai.egg-info/SOURCES.txt
powerline_exitstatus_kai.egg-info/dependency_links.txt
powerline_exitstatus_kai.egg-info/requires.txt
powerline_exitstatus_kai.egg-info/top_level.txt