Metadata-Version: 1.1
Name: powerline-exitstatus-kai
Version: 1.2.0
Summary: A Powerline segment for showing the status of Exit status
Home-page: https://github.com/i0ntempest/powerline-exitstatus-kai
Author: i0ntempest
Author-email: szf1234@me.com
License: MIT
Download-URL: https://github.com/i0ntempest/powerline-exitstatus-kai/archive/v1.2.0.tar.gz
Keywords: powerline exit status prompt,powerline,shell,console
Platform: UNKNOWN
Classifier: Environment :: Console
Classifier: Intended Audience :: Developers
Classifier: License :: OSI Approved :: MIT License
Classifier: Topic :: Terminals
